im_gcscacher/__init__.py
im_gcscacher-0.1.1.dist-info/DESCRIPTION.rst
im_gcscacher-0.1.1.dist-info/METADATA
im_gcscacher-0.1.1.dist-info/RECORD
im_gcscacher-0.1.1.dist-info/WHEEL
im_gcscacher-0.1.1.dist-info/metadata.json
im_gcscacher-0.1.1.dist-info/top_level.txt
