Metadata-Version: 2.0
Name: im-gcscacher
Version: 0.1.1
Summary: A decorator for caching into gcs on google app engine, python standard environment
Home-page: https://github.com/emlynoregan/im_gcscacher
Author: Emlyn O'Regan
Author-email: emlynoregan@gmail.com
License: ../LICENSE.txt
Platform: UNKNOWN
Classifier: Development Status :: 3 - Alpha
Classifier: Intended Audience :: Developers
Classifier: License :: OSI Approved :: Apache Software License
Classifier: Operating System :: POSIX
Classifier: Operating System :: Microsoft :: Windows
Classifier: Operating System :: MacOS :: MacOS X
Classifier: Programming Language :: Python :: 2.7
Classifier: Programming Language :: Python :: Implementation :: CPython
Classifier: Topic :: Software Development :: Libraries :: Python Modules
Classifier: Topic :: System :: Distributed Computing
Requires-Dist: im-util
Requires-Dist: GoogleAppEngineCloudStorageClient
Requires-Dist: cloudpickle
